fglib/__init__.py
fglib/atrlib.py
fglib/financialGraph.py
fglib/kagilib.py
fglib/linebreaklib.py
fglib/pnflib.py
fglib/renkolib.py
Financial_Graph_Lib-1.0.4.dist-info/LICENSE
Financial_Graph_Lib-1.0.4.dist-info/METADATA
Financial_Graph_Lib-1.0.4.dist-info/WHEEL
Financial_Graph_Lib-1.0.4.dist-info/top_level.txt
Financial_Graph_Lib-1.0.4.dist-info/RECORD
