Metadata-Version: 2.1
Name: Financial-Graph-Lib
Version: 1.0.4
Summary: Financial graph lib for different stock market graph
Home-page: https://github.com/kUNWAR-DIVYANSHU/Financial-Graph-Lib
Author: Homofabers Stock Devs
Author-email: kdivyanshu3@gmail.com
License: MIT
Keywords: finance graph stocks analysis line area baseline candle hollow hollowcandle renko pnf point and figure
Platform: UNKNOWN
Classifier: Programming Language :: Python :: 3
Classifier: License :: OSI Approved :: MIT License
Classifier: Operating System :: OS Independent
Requires-Python: >=3.6
License-File: LICENSE
Requires-Dist: pandas
Requires-Dist: numpy
Requires-Dist: matplotlib
